MANIFEST.in
README.rst
dyploy.py
setup.py
dyploy.egg-info/PKG-INFO
dyploy.egg-info/SOURCES.txt
dyploy.egg-info/dependency_links.txt
dyploy.egg-info/entry_points.txt
dyploy.egg-info/requires.txt
dyploy.egg-info/top_level.txt
dyploy.egg-info/zip-safe
templates/.dyploy.yml.example