Metadata-Version: 1.0
Name: dyploy
Version: 0.4.3
Summary: dyploy
Home-page: https://example.org
Author: me
Author-email: me@example.org
License: LGPL v3
Keywords: dyploy
Platform: UNKNOWN
